zender/__init__.py
zender/cli.py
zender-0.0.1.dist-info/LICENSE
zender-0.0.1.dist-info/METADATA
zender-0.0.1.dist-info/WHEEL
zender-0.0.1.dist-info/entry_points.txt
zender-0.0.1.dist-info/top_level.txt
zender-0.0.1.dist-info/RECORD
