Metadata-Version: 2.1
Name: zender
Version: 0.0.1
Classifier: Programming Language :: Python :: 3
Requires-Python: >=3.7, <4
License-File: LICENSE
Requires-Dist: Jinja2
Requires-Dist: click
